LICENSE
MANIFEST.in
README.md
README.rst
setup.py
test_execjs.py
PyExecJS.egg-info/PKG-INFO
PyExecJS.egg-info/SOURCES.txt
PyExecJS.egg-info/dependency_links.txt
PyExecJS.egg-info/requires.txt
PyExecJS.egg-info/top_level.txt
execjs/__init__.py
execjs/__main__.py
execjs/_abstract_runtime.py
execjs/_abstract_runtime_context.py
execjs/_exceptions.py
execjs/_external_runtime.py
execjs/_json2.py
execjs/_misc.py
execjs/_pyv8runtime.py
execjs/_runner_sources.py
execjs/_runtimes.py